{
  "registerButtonText": "Register",
  "eventLogo": "",
  "actionBarColor": "#45657f",
  "eventDate": "2026-08-07T19:00:00.000-05:00",
  "eventInfo": "Crush your PR and run your fastest mile! \n\nJoin us to challenge yourself and claim your 1 Mile PR. \n\nPrice: $15\nTime:7:30PM EDT-9:00PM CDT\n\nLocation:\nStillwater Junior High School\n\n1900 N Skyline St, Stillwater, OK 74075",
  "bannerImage": "/assets/img_4578.png",
  "venue": "Stillwater Junior High School Track",
  "registerLink": "https://runsignup.com/Race/OK/Stillwater/TheAbsoluteSendOneMileChallenge",
  "eventTitle": "The Absolute Send "
}